{
  "version": "7",
  "dialect": "postgresql",
  "entries": [
    {
      "idx": 0,
      "version": "7",
      "when": 1774909081932,
      "tag": "0000_wonderful_shinobi_shaw",
      "breakpoints": true
    },
    {
      "idx": 1,
      "version": "7",
      "when": 1774938459092,
      "tag": "0001_nebulous_shinko_yamashiro",
      "breakpoints": true
    },
    {
      "idx": 2,
      "version": "7",
      "when": 1774947018541,
      "tag": "0002_motionless_ogun",
      "breakpoints": true
    },
    {
      "idx": 3,
      "version": "7",
      "when": 1774984229389,
      "tag": "0003_striped_black_bird",
      "breakpoints": true
    },
    {
      "idx": 4,
      "version": "7",
      "when": 1775109067827,
      "tag": "0004_absurd_sphinx",
      "breakpoints": true
    },
    {
      "idx": 5,
      "version": "7",
      "when": 1775174400000,
      "tag": "0005_bright_photos",
      "breakpoints": true
    },
    {
      "idx": 6,
      "version": "7",
      "when": 1775174460000,
      "tag": "0006_student_section_relation",
      "breakpoints": true
    }
  ]
}